enumeraite/__init__.py
enumeraite/cli/__init__.py
enumeraite/cli/commands.py
enumeraite/cli/main.py
enumeraite/cli/ui.py
enumeraite/core/__init__.py
enumeraite/core/config.py
enumeraite/core/dns_validator.py
enumeraite/core/engine.py
enumeraite/core/factory.py
enumeraite/core/http_validator.py
enumeraite/core/models.py
enumeraite/core/path_function_analysis.py
enumeraite/core/pattern_analysis.py
enumeraite/core/provider.py
enumeraite/core/strategies.py
enumeraite/providers/__init__.py
enumeraite/providers/claude_provider.py
enumeraite/providers/huggingface_provider.py
enumeraite/providers/openai_provider.py
enumeraite-0.1.4.dist-info/licenses/LICENSE
enumeraite-0.1.4.dist-info/METADATA
enumeraite-0.1.4.dist-info/WHEEL
enumeraite-0.1.4.dist-info/entry_points.txt
enumeraite-0.1.4.dist-info/top_level.txt
enumeraite-0.1.4.dist-info/RECORD
