Metadata-Version: 2.4
Name: enumeraite
Version: 0.1.4
Summary: AI-Powered Web Attack Surface Enumeration - The future of intelligent discovery
Author-email: Özgün Kültekin <ozgun@enumeraite.com>
License: MIT License
Project-URL: Homepage, https://enumeraite.com
Project-URL: Documentation, https://enumeraite.com
Project-URL: Repository, https://github.com/oz9un/enumeraite
Project-URL: Bug Reports, https://github.com/oz9un/enumeraite/issues
Project-URL: Funding, https://github.com/sponsors/oz9un
Keywords: enumeration,security,ai,pentesting,bug-bounty,subdomain-enumeration,path-discovery,attack-surface,reconnaissance,cybersecurity
Classifier: Development Status :: 3 - Alpha
Classifier: Intended Audience :: Information Technology
Classifier: Intended Audience :: Developers
Classifier: License :: OSI Approved :: MIT License
Classifier: Programming Language :: Python :: 3
Classifier: Programming Language :: Python :: 3.9
Classifier: Programming Language :: Python :: 3.10
Classifier: Programming Language :: Python :: 3.11
Classifier: Programming Language :: Python :: 3.12
Classifier: Topic :: Security
Classifier: Topic :: Software Development :: Testing
Classifier: Topic :: Internet :: WWW/HTTP
Classifier: Operating System :: OS Independent
Requires-Python: >=3.9
License-File: LICENSE
Requires-Dist: click>=8.0.0
Requires-Dist: aiohttp>=3.8.0
Requires-Dist: pydantic>=2.0.0
Requires-Dist: requests>=2.25.0
Requires-Dist: anthropic>=0.7.0
Requires-Dist: openai>=1.0.0
Provides-Extra: huggingface
Requires-Dist: transformers>=4.30.0; extra == "huggingface"
Requires-Dist: torch>=2.0.0; extra == "huggingface"
Provides-Extra: all
Requires-Dist: transformers>=4.30.0; extra == "all"
Requires-Dist: torch>=2.0.0; extra == "all"
Provides-Extra: dev
Requires-Dist: pytest>=7.0.0; extra == "dev"
Requires-Dist: pytest-asyncio>=0.21.0; extra == "dev"
Requires-Dist: black>=23.0.0; extra == "dev"
Requires-Dist: isort>=5.12.0; extra == "dev"
Requires-Dist: mypy>=1.5.0; extra == "dev"
Dynamic: license-file
